README.md
setup.cfg
setup.py
sdic/__init__.py
sdic/constants.py
sdic/main.py
sdic.egg-info/PKG-INFO
sdic.egg-info/SOURCES.txt
sdic.egg-info/dependency_links.txt
sdic.egg-info/entry_points.txt
sdic.egg-info/requires.txt
sdic.egg-info/top_level.txt