Metadata-Version: 1.1
Name: sdic
Version: 0.2.1
Summary: Asynchronous soft constraints executed against you databases
Home-page: https://github.com/percolate/sdic
Author: Laurent Raufaste
Author-email: analogue@glop.org
License: GPLv3
Keywords: sdic sql mysql postgresql sqlalchemy data integrity constraints
Platform: UNKNOWN
Classifier: Development Status :: 4 - Beta
Classifier: Environment :: Console
Classifier: Intended Audience :: End Users/Desktop
Classifier: License :: OSI Approved :: GNU General Public License v3 or later (GPLv3+)
Classifier: Natural Language :: English
Classifier: Operating System :: POSIX
Classifier: Programming Language :: Python
Classifier: Topic :: Utilities
